[
  {
    "id":"f30c681b-65b3-45d1-8854-cf0f935a5ad7",
    "symbol":"BENCHMARK",
    "side":"buy",
    "order_type":"market",
    "quantity":34700.0,
    "filled_quantity":34700.0,
    "limit_price":null,
    "stop_price":null,
    "avg_price":29.4,
    "commission":149.97969,
    "status":"filled",
    "time_in_force":"gtc",
    "created_at":"2023-04-06T16:00:00.000Z",
    "updated_at":"2023-04-10T16:00:00.000Z",
    "tag":"",
    "reject_reason":"",
    "filled_value":1020180.0,
    "duration":"P4DT0H0M0S"
  },
  {
    "id":"8bd12ab0-aba5-4346-b517-eb480293884c",
    "symbol":"BENCHMARK",
    "side":"sell",
    "order_type":"market",
    "quantity":34009.0,
    "filled_quantity":34009.0,
    "limit_price":null,
    "stop_price":null,
    "avg_price":30.91,
    "commission":157.6827285,
    "status":"filled",
    "time_in_force":"gtc",
    "created_at":"2023-05-31T16:00:00.000Z",
    "updated_at":"2023-06-04T16:00:00.000Z",
    "tag":"",
    "reject_reason":"",
    "filled_value":1051218.1899999999,
    "duration":"P4DT0H0M0S"
  },
  {
    "id":"88097c2d-e30c-4292-aec4-5996a365d203",
    "symbol":"BENCHMARK",
    "side":"buy",
    "order_type":"market",
    "quantity":36200.0,
    "filled_quantity":36200.0,
    "limit_price":null,
    "stop_price":null,
    "avg_price":28.7,
    "commission":155.841,
    "status":"filled",
    "time_in_force":"gtc",
    "created_at":"2023-07-25T16:00:00.000Z",
    "updated_at":"2023-07-27T16:00:00.000Z",
    "tag":"",
    "reject_reason":"",
    "filled_value":1038940.0,
    "duration":"P2DT0H0M0S"
  },
  {
    "id":"3e53e8b6-3001-4d32-89a0-c7800b5a52b7",
    "symbol":"BENCHMARK",
    "side":"sell",
    "order_type":"market",
    "quantity":36200.0,
    "filled_quantity":36200.0,
    "limit_price":null,
    "stop_price":null,
    "avg_price":28.69,
    "commission":155.7867,
    "status":"filled",
    "time_in_force":"gtc",
    "created_at":"2023-07-27T16:00:00.000Z",
    "updated_at":"2023-07-30T16:00:00.000Z",
    "tag":"",
    "reject_reason":"",
    "filled_value":1038578.0,
    "duration":"P3DT0H0M0S"
  },
  {
    "id":"9d69fe2d-1e68-4ca0-8cbb-45b66f673d0f",
    "symbol":"BENCHMARK",
    "side":"buy",
    "order_type":"market",
    "quantity":38200.0,
    "filled_quantity":38200.0,
    "limit_price":null,
    "stop_price":null,
    "avg_price":28.81,
    "commission":157.5316395,
    "status":"filled",
    "time_in_force":"gtc",
    "created_at":"2023-08-24T16:00:00.000Z",
    "updated_at":"2023-08-27T16:00:00.000Z",
    "tag":"",
    "reject_reason":"",
    "filled_value":1100542.0,
    "duration":"P3DT0H0M0S"
  },
  {
    "id":"0fe56bc1-d950-4643-acb3-0275c0cb6192",
    "symbol":"BENCHMARK",
    "side":"sell",
    "order_type":"market",
    "quantity":36453.0,
    "filled_quantity":36453.0,
    "limit_price":null,
    "stop_price":null,
    "avg_price":26.68,
    "commission":145.884906,
    "status":"filled",
    "time_in_force":"gtc",
    "created_at":"2023-08-31T16:00:00.000Z",
    "updated_at":"2023-09-03T16:00:00.000Z",
    "tag":"",
    "reject_reason":"",
    "filled_value":972566.04,
    "duration":"P3DT0H0M0S"
  },
  {
    "id":"5d09b9a8-482a-4ea0-bd3f-c9d680521ad6",
    "symbol":"BENCHMARK",
    "side":"buy",
    "order_type":"market",
    "quantity":35000.0,
    "filled_quantity":35000.0,
    "limit_price":null,
    "stop_price":null,
    "avg_price":27.76,
    "commission":145.74,
    "status":"filled",
    "time_in_force":"gtc",
    "created_at":"2023-09-10T16:00:00.000Z",
    "updated_at":"2023-09-12T16:00:00.000Z",
    "tag":"",
    "reject_reason":"",
    "filled_value":971600.0,
    "duration":"P2DT0H0M0S"
  },
  {
    "id":"17d020b0-72af-4688-aa0f-35164363316f",
    "symbol":"BENCHMARK",
    "side":"sell",
    "order_type":"market",
    "quantity":35000.0,
    "filled_quantity":35000.0,
    "limit_price":null,
    "stop_price":null,
    "avg_price":27.46,
    "commission":144.165,
    "status":"filled",
    "time_in_force":"gtc",
    "created_at":"2023-10-18T16:00:00.000Z",
    "updated_at":"2023-10-19T16:00:00.000Z",
    "tag":"",
    "reject_reason":"",
    "filled_value":961100.0,
    "duration":"P1DT0H0M0S"
  },
  {
    "id":"32f1a779-dafa-45b7-9ba9-45f1facf1184",
    "symbol":"BENCHMARK",
    "side":"buy",
    "order_type":"market",
    "quantity":34300.0,
    "filled_quantity":34300.0,
    "limit_price":null,
    "stop_price":null,
    "avg_price":28.43,
    "commission":144.22539,
    "status":"filled",
    "time_in_force":"gtc",
    "created_at":"2023-11-06T16:00:00.000Z",
    "updated_at":"2023-11-08T16:00:00.000Z",
    "tag":"",
    "reject_reason":"",
    "filled_value":975149.0,
    "duration":"P2DT0H0M0S"
  },
  {
    "id":"3df7b18d-d064-44df-8720-9a7e1deeb007",
    "symbol":"BENCHMARK",
    "side":"sell",
    "order_type":"market",
    "quantity":33820.0,
    "filled_quantity":33820.0,
    "limit_price":null,
    "stop_price":null,
    "avg_price":27.64,
    "commission":140.21772,
    "status":"filled",
    "time_in_force":"gtc",
    "created_at":"2023-11-08T16:00:00.000Z",
    "updated_at":"2023-11-09T16:00:00.000Z",
    "tag":"",
    "reject_reason":"",
    "filled_value":934784.8,
    "duration":"P1DT0H0M0S"
  },
  {
    "id":"459035c1-eedd-46ec-8f4a-0921ba2eaad5",
    "symbol":"BENCHMARK",
    "side":"buy",
    "order_type":"market",
    "quantity":33500.0,
    "filled_quantity":33500.0,
    "limit_price":null,
    "stop_price":null,
    "avg_price":27.83,
    "commission":139.84575,
    "status":"filled",
    "time_in_force":"gtc",
    "created_at":"2023-11-20T16:00:00.000Z",
    "updated_at":"2023-11-22T16:00:00.000Z",
    "tag":"",
    "reject_reason":"",
    "filled_value":932305.0,
    "duration":"P2DT0H0M0S"
  },
  {
    "id":"aa1e9f28-9a60-41fe-9083-0b9e6c292ee7",
    "symbol":"BENCHMARK",
    "side":"sell",
    "order_type":"market",
    "quantity":33500.0,
    "filled_quantity":33500.0,
    "limit_price":null,
    "stop_price":null,
    "avg_price":27.68,
    "commission":139.092,
    "status":"filled",
    "time_in_force":"gtc",
    "created_at":"2024-01-04T16:00:00.000Z",
    "updated_at":"2024-01-07T16:00:00.000Z",
    "tag":"",
    "reject_reason":"",
    "filled_value":927280.0,
    "duration":"P3DT0H0M0S"
  },
  {
    "id":"5ea2546d-598e-460d-bcff-826f3e3da64d",
    "symbol":"BENCHMARK",
    "side":"buy",
    "order_type":"market",
    "quantity":34900.0,
    "filled_quantity":34900.0,
    "limit_price":null,
    "stop_price":null,
    "avg_price":26.4,
    "commission":138.204,
    "status":"filled",
    "time_in_force":"gtc",
    "created_at":"2024-02-06T16:00:00.000Z",
    "updated_at":"2024-02-07T16:00:00.000Z",
    "tag":"",
    "reject_reason":"",
    "filled_value":921360.0,
    "duration":"P1DT0H0M0S"
  },
  {
    "id":"20d68150-c74b-40bf-9a56-a3e4befa0c6a",
    "symbol":"BENCHMARK",
    "side":"sell",
    "order_type":"market",
    "quantity":34900.0,
    "filled_quantity":34900.0,
    "limit_price":null,
    "stop_price":null,
    "avg_price":25.7,
    "commission":134.5395,
    "status":"filled",
    "time_in_force":"gtc",
    "created_at":"2024-02-21T16:00:00.000Z",
    "updated_at":"2024-02-22T16:00:00.000Z",
    "tag":"",
    "reject_reason":"",
    "filled_value":896930.0,
    "duration":"P1DT0H0M0S"
  },
  {
    "id":"412acdab-4080-48f3-8950-b758acf4ed69",
    "symbol":"BENCHMARK",
    "side":"buy",
    "order_type":"market",
    "quantity":33800.0,
    "filled_quantity":33800.0,
    "limit_price":null,
    "stop_price":null,
    "avg_price":26.61,
    "commission":134.9127,
    "status":"filled",
    "time_in_force":"gtc",
    "created_at":"2024-02-26T16:00:00.000Z",
    "updated_at":"2024-02-28T16:00:00.000Z",
    "tag":"",
    "reject_reason":"",
    "filled_value":899418.0,
    "duration":"P2DT0H0M0S"
  },
  {
    "id":"793d5d4c-4bf6-434e-a788-084d4e7bc47b",
    "symbol":"BENCHMARK",
    "side":"sell",
    "order_type":"market",
    "quantity":33800.0,
    "filled_quantity":33800.0,
    "limit_price":null,
    "stop_price":null,
    "avg_price":29.88,
    "commission":151.4916,
    "status":"filled",
    "time_in_force":"gtc",
    "created_at":"2024-04-15T16:00:00.000Z",
    "updated_at":"2024-04-17T16:00:00.000Z",
    "tag":"",
    "reject_reason":"",
    "filled_value":1009944.0,
    "duration":"P2DT0H0M0S"
  },
  {
    "id":"f27e6afa-d494-4c72-bb49-e17bc5b9a4f5",
    "symbol":"BENCHMARK",
    "side":"buy",
    "order_type":"market",
    "quantity":34200.0,
    "filled_quantity":34200.0,
    "limit_price":null,
    "stop_price":null,
    "avg_price":29.17,
    "commission":149.6421,
    "status":"filled",
    "time_in_force":"gtc",
    "created_at":"2024-04-17T16:00:00.000Z",
    "updated_at":"2024-04-21T16:00:00.000Z",
    "tag":"",
    "reject_reason":"",
    "filled_value":997614.0000000001,
    "duration":"P4DT0H0M0S"
  },
  {
    "id":"c604330a-1f7c-4dbf-9956-26103f14f21e",
    "symbol":"BENCHMARK",
    "side":"sell",
    "order_type":"market",
    "quantity":34200.0,
    "filled_quantity":34200.0,
    "limit_price":null,
    "stop_price":null,
    "avg_price":32.81,
    "commission":168.3153,
    "status":"filled",
    "time_in_force":"gtc",
    "created_at":"2024-05-29T16:00:00.000Z",
    "updated_at":"2024-05-30T16:00:00.000Z",
    "tag":"",
    "reject_reason":"",
    "filled_value":1122102.0,
    "duration":"P1DT0H0M0S"
  },
  {
    "id":"477eb99a-8ea8-416d-b56c-11cfd917078e",
    "symbol":"BENCHMARK",
    "side":"buy",
    "order_type":"market",
    "quantity":34200.0,
    "filled_quantity":34200.0,
    "limit_price":null,
    "stop_price":null,
    "avg_price":33.32,
    "commission":170.83164,
    "status":"filled",
    "time_in_force":"gtc",
    "created_at":"2024-06-03T16:00:00.000Z",
    "updated_at":"2024-06-04T16:00:00.000Z",
    "tag":"",
    "reject_reason":"",
    "filled_value":1139544.0,
    "duration":"P1DT0H0M0S"
  },
  {
    "id":"743eb2a6-3bfb-4dab-8756-f5867cfe6a47",
    "symbol":"BENCHMARK",
    "side":"sell",
    "order_type":"market",
    "quantity":34180.0,
    "filled_quantity":34180.0,
    "limit_price":null,
    "stop_price":null,
    "avg_price":32.23,
    "commission":165.24321,
    "status":"filled",
    "time_in_force":"gtc",
    "created_at":"2024-06-06T16:00:00.000Z",
    "updated_at":"2024-06-11T16:00:00.000Z",
    "tag":"",
    "reject_reason":"",
    "filled_value":1101621.3999999999,
    "duration":"P5DT0H0M0S"
  },
  {
    "id":"6a1e375f-de3c-4b93-9f6b-ea70c60953c9",
    "symbol":"BENCHMARK",
    "side":"buy",
    "order_type":"market",
    "quantity":34600.0,
    "filled_quantity":34600.0,
    "limit_price":null,
    "stop_price":null,
    "avg_price":31.55,
    "commission":163.7445,
    "status":"filled",
    "time_in_force":"gtc",
    "created_at":"2024-07-14T16:00:00.000Z",
    "updated_at":"2024-07-16T16:00:00.000Z",
    "tag":"",
    "reject_reason":"",
    "filled_value":1091630.0,
    "duration":"P2DT0H0M0S"
  },
  {
    "id":"57714b8e-856f-4493-8e7f-4b318e918e7d",
    "symbol":"BENCHMARK",
    "side":"sell",
    "order_type":"market",
    "quantity":34600.0,
    "filled_quantity":34600.0,
    "limit_price":null,
    "stop_price":null,
    "avg_price":30.54,
    "commission":158.5026,
    "status":"filled",
    "time_in_force":"gtc",
    "created_at":"2024-07-23T16:00:00.000Z",
    "updated_at":"2024-07-24T16:00:00.000Z",
    "tag":"",
    "reject_reason":"",
    "filled_value":1056684.0,
    "duration":"P1DT0H0M0S"
  },
  {
    "id":"f26e4199-4bbc-4408-8ce1-c330e1e7d952",
    "symbol":"BENCHMARK",
    "side":"buy",
    "order_type":"market",
    "quantity":34100.0,
    "filled_quantity":34100.0,
    "limit_price":null,
    "stop_price":null,
    "avg_price":31.16,
    "commission":159.3834,
    "status":"filled",
    "time_in_force":"gtc",
    "created_at":"2024-08-11T16:00:00.000Z",
    "updated_at":"2024-08-13T16:00:00.000Z",
    "tag":"",
    "reject_reason":"",
    "filled_value":1062556.0,
    "duration":"P2DT0H0M0S"
  },
  {
    "id":"87054b72-9472-4b28-9b42-975a3264c2a5",
    "symbol":"BENCHMARK",
    "side":"sell",
    "order_type":"market",
    "quantity":34100.0,
    "filled_quantity":34100.0,
    "limit_price":null,
    "stop_price":null,
    "avg_price":31.2,
    "commission":159.588,
    "status":"filled",
    "time_in_force":"gtc",
    "created_at":"2024-08-14T16:00:00.000Z",
    "updated_at":"2024-08-18T16:00:00.000Z",
    "tag":"",
    "reject_reason":"",
    "filled_value":1063920.0,
    "duration":"P4DT0H0M0S"
  },
  {
    "id":"d9771189-ff5e-4dc6-b924-e0e3acf442fa",
    "symbol":"BENCHMARK",
    "side":"buy",
    "order_type":"market",
    "quantity":33900.0,
    "filled_quantity":33900.0,
    "limit_price":null,
    "stop_price":null,
    "avg_price":31.3,
    "commission":159.1605,
    "status":"filled",
    "time_in_force":"gtc",
    "created_at":"2024-08-18T16:00:00.000Z",
    "updated_at":"2024-08-20T16:00:00.000Z",
    "tag":"",
    "reject_reason":"",
    "filled_value":1061070.0,
    "duration":"P2DT0H0M0S"
  },
  {
    "id":"08f0bd50-a491-4ac9-826d-65346d03e1b8",
    "symbol":"BENCHMARK",
    "side":"sell",
    "order_type":"market",
    "quantity":33900.0,
    "filled_quantity":33900.0,
    "limit_price":null,
    "stop_price":null,
    "avg_price":30.82,
    "commission":156.7197,
    "status":"filled",
    "time_in_force":"gtc",
    "created_at":"2024-09-01T16:00:00.000Z",
    "updated_at":"2024-09-03T16:00:00.000Z",
    "tag":"",
    "reject_reason":"",
    "filled_value":1044798.0,
    "duration":"P2DT0H0M0S"
  },
  {
    "id":"3fc275bf-aa3a-426c-abef-0c718f6b767a",
    "symbol":"BENCHMARK",
    "side":"buy",
    "order_type":"market",
    "quantity":33200.0,
    "filled_quantity":33200.0,
    "limit_price":null,
    "stop_price":null,
    "avg_price":31.6,
    "commission":157.368,
    "status":"filled",
    "time_in_force":"gtc",
    "created_at":"2024-09-03T16:00:00.000Z",
    "updated_at":"2024-09-04T16:00:00.000Z",
    "tag":"",
    "reject_reason":"",
    "filled_value":1049120.0,
    "duration":"P1DT0H0M0S"
  },
  {
    "id":"1c3bdb27-975b-4e50-b0f2-2c66579196cc",
    "symbol":"BENCHMARK",
    "side":"sell",
    "order_type":"market",
    "quantity":33200.0,
    "filled_quantity":33200.0,
    "limit_price":null,
    "stop_price":null,
    "avg_price":30.05,
    "commission":149.649,
    "status":"filled",
    "time_in_force":"gtc",
    "created_at":"2024-09-11T16:00:00.000Z",
    "updated_at":"2024-09-17T16:00:00.000Z",
    "tag":"",
    "reject_reason":"",
    "filled_value":997660.0,
    "duration":"P6DT0H0M0S"
  },
  {
    "id":"2fe35b51-f7cb-4755-bf6f-21deb851daba",
    "symbol":"BENCHMARK",
    "side":"buy",
    "order_type":"market",
    "quantity":33600.0,
    "filled_quantity":33600.0,
    "limit_price":null,
    "stop_price":null,
    "avg_price":30.54,
    "commission":149.807862,
    "status":"filled",
    "time_in_force":"gtc",
    "created_at":"2024-09-26T16:00:00.000Z",
    "updated_at":"2024-09-29T16:00:00.000Z",
    "tag":"",
    "reject_reason":"",
    "filled_value":1026144.0,
    "duration":"P3DT0H0M0S"
  },
  {
    "id":"24118e9d-5cbd-4e76-b4df-33b078bde70a",
    "symbol":"BENCHMARK",
    "side":"sell",
    "order_type":"market",
    "quantity":32702.0,
    "filled_quantity":32702.0,
    "limit_price":null,
    "stop_price":null,
    "avg_price":31.13,
    "commission":152.701989,
    "status":"filled",
    "time_in_force":"gtc",
    "created_at":"2024-11-13T16:00:00.000Z",
    "updated_at":"2024-11-17T16:00:00.000Z",
    "tag":"",
    "reject_reason":"",
    "filled_value":1018013.26,
    "duration":"P4DT0H0M0S"
  },
  {
    "id":"0a2d20bb-3df8-4268-8532-607e05c3cbb4",
    "symbol":"BENCHMARK",
    "side":"buy",
    "order_type":"market",
    "quantity":31100.0,
    "filled_quantity":31100.0,
    "limit_price":null,
    "stop_price":null,
    "avg_price":32.67,
    "commission":152.40555,
    "status":"filled",
    "time_in_force":"gtc",
    "created_at":"2024-11-26T16:00:00.000Z",
    "updated_at":"2024-11-27T16:00:00.000Z",
    "tag":"",
    "reject_reason":"",
    "filled_value":1016037.0,
    "duration":"P1DT0H0M0S"
  },
  {
    "id":"98709fe0-a536-4e13-b45d-cb88e4d74a21",
    "symbol":"BENCHMARK",
    "side":"sell",
    "order_type":"market",
    "quantity":31100.0,
    "filled_quantity":31100.0,
    "limit_price":null,
    "stop_price":null,
    "avg_price":31.7,
    "commission":147.8805,
    "status":"filled",
    "time_in_force":"gtc",
    "created_at":"2024-12-11T16:00:00.000Z",
    "updated_at":"2024-12-15T16:00:00.000Z",
    "tag":"",
    "reject_reason":"",
    "filled_value":985870.0,
    "duration":"P4DT0H0M0S"
  },
  {
    "id":"828ac4ce-29f0-4ffa-a543-3cef58f59ebe",
    "symbol":"BENCHMARK",
    "side":"buy",
    "order_type":"market",
    "quantity":34700.0,
    "filled_quantity":34700.0,
    "limit_price":null,
    "stop_price":null,
    "avg_price":28.2,
    "commission":146.781,
    "status":"filled",
    "time_in_force":"gtc",
    "created_at":"2025-02-23T16:00:00.000Z",
    "updated_at":"2025-02-25T16:00:00.000Z",
    "tag":"",
    "reject_reason":"",
    "filled_value":978540.0,
    "duration":"P2DT0H0M0S"
  },
  {
    "id":"96967bd9-a2da-4d61-8ff9-6ed499730e84",
    "symbol":"BENCHMARK",
    "side":"sell",
    "order_type":"market",
    "quantity":34700.0,
    "filled_quantity":34700.0,
    "limit_price":null,
    "stop_price":null,
    "avg_price":32.76,
    "commission":170.5158,
    "status":"filled",
    "time_in_force":"gtc",
    "created_at":"2025-04-24T16:00:00.000Z",
    "updated_at":"2025-04-28T16:00:00.000Z",
    "tag":"",
    "reject_reason":"",
    "filled_value":1136772.0,
    "duration":"P4DT0H0M0S"
  },
  {
    "id":"95f2ffdf-6de6-4fda-ba4f-fdb9b26bcad7",
    "symbol":"BENCHMARK",
    "side":"buy",
    "order_type":"market",
    "quantity":32000.0,
    "filled_quantity":32000.0,
    "limit_price":null,
    "stop_price":null,
    "avg_price":35.91,
    "commission":171.7700985,
    "status":"filled",
    "time_in_force":"gtc",
    "created_at":"2025-05-05T16:00:00.000Z",
    "updated_at":"2025-05-06T16:00:00.000Z",
    "tag":"",
    "reject_reason":"",
    "filled_value":1149120.0,
    "duration":"P1DT0H0M0S"
  },
  {
    "id":"f61d291a-e3cc-4e88-bfb9-54a594acf0ff",
    "symbol":"BENCHMARK",
    "side":"sell",
    "order_type":"market",
    "quantity":31889.0,
    "filled_quantity":31889.0,
    "limit_price":null,
    "stop_price":null,
    "avg_price":33.62,
    "commission":160.816227,
    "status":"filled",
    "time_in_force":"gtc",
    "created_at":"2025-05-08T16:00:00.000Z",
    "updated_at":"2025-05-12T16:00:00.000Z",
    "tag":"",
    "reject_reason":"",
    "filled_value":1072108.1799999999,
    "duration":"P4DT0H0M0S"
  },
  {
    "id":"105c4044-9a11-48fd-b59e-2d16010ce071",
    "symbol":"BENCHMARK",
    "side":"buy",
    "order_type":"market",
    "quantity":30600.0,
    "filled_quantity":30600.0,
    "limit_price":null,
    "stop_price":null,
    "avg_price":34.96,
    "commission":160.4664,
    "status":"filled",
    "time_in_force":"gtc",
    "created_at":"2025-05-15T16:00:00.000Z",
    "updated_at":"2025-05-19T16:00:00.000Z",
    "tag":"",
    "reject_reason":"",
    "filled_value":1069776.0,
    "duration":"P4DT0H0M0S"
  },
  {
    "id":"91906449-c76c-4d8d-9006-28b8e55f633b",
    "symbol":"BENCHMARK",
    "side":"sell",
    "order_type":"market",
    "quantity":30600.0,
    "filled_quantity":30600.0,
    "limit_price":null,
    "stop_price":null,
    "avg_price":34.94,
    "commission":160.3746,
    "status":"filled",
    "time_in_force":"gtc",
    "created_at":"2025-06-15T16:00:00.000Z",
    "updated_at":"2025-06-17T16:00:00.000Z",
    "tag":"",
    "reject_reason":"",
    "filled_value":1069164.0,
    "duration":"P2DT0H0M0S"
  },
  {
    "id":"c3637101-ea65-40fb-a6c2-0e0f76a5e5c4",
    "symbol":"BENCHMARK",
    "side":"buy",
    "order_type":"market",
    "quantity":30400.0,
    "filled_quantity":30400.0,
    "limit_price":null,
    "stop_price":null,
    "avg_price":35.29,
    "commission":160.625964,
    "status":"filled",
    "time_in_force":"gtc",
    "created_at":"2025-07-27T16:00:00.000Z",
    "updated_at":"2025-07-28T16:00:00.000Z",
    "tag":"",
    "reject_reason":"",
    "filled_value":1072816.0,
    "duration":"P1DT0H0M0S"
  },
  {
    "id":"99dbfa10-161e-409f-a9a4-a06df6e38aff",
    "symbol":"BENCHMARK",
    "side":"sell",
    "order_type":"market",
    "quantity":30344.0,
    "filled_quantity":30344.0,
    "limit_price":null,
    "stop_price":null,
    "avg_price":37.28,
    "commission":169.683648,
    "status":"filled",
    "time_in_force":"gtc",
    "created_at":"2025-09-10T16:00:00.000Z",
    "updated_at":"2025-09-14T16:00:00.000Z",
    "tag":"",
    "reject_reason":"",
    "filled_value":1131224.3200000001,
    "duration":"P4DT0H0M0S"
  },
  {
    "id":"9fe5196f-0bc7-452d-8357-1f97dd32cd0b",
    "symbol":"BENCHMARK",
    "side":"buy",
    "order_type":"market",
    "quantity":32600.0,
    "filled_quantity":32600.0,
    "limit_price":null,
    "stop_price":null,
    "avg_price":34.47,
    "commission":168.5583,
    "status":"filled",
    "time_in_force":"gtc",
    "created_at":"2025-11-25T16:00:00.000Z",
    "updated_at":"2025-11-27T16:00:00.000Z",
    "tag":"",
    "reject_reason":"",
    "filled_value":1123722.0,
    "duration":"P2DT0H0M0S"
  },
  {
    "id":"b9efbdd6-e220-42d6-809c-20e18f8764d0",
    "symbol":"BENCHMARK",
    "side":"sell",
    "order_type":"market",
    "quantity":32600.0,
    "filled_quantity":32600.0,
    "limit_price":null,
    "stop_price":null,
    "avg_price":34.29,
    "commission":167.6781,
    "status":"filled",
    "time_in_force":"gtc",
    "created_at":"2025-12-02T16:00:00.000Z",
    "updated_at":"2025-12-04T16:00:00.000Z",
    "tag":"",
    "reject_reason":"",
    "filled_value":1117854.0,
    "duration":"P2DT0H0M0S"
  },
  {
    "id":"66d80bc8-c6c5-43bc-81e7-743c9a74c6ca",
    "symbol":"BENCHMARK",
    "side":"buy",
    "order_type":"market",
    "quantity":35700.0,
    "filled_quantity":35700.0,
    "limit_price":null,
    "stop_price":null,
    "avg_price":33.15,
    "commission":168.70698,
    "status":"filled",
    "time_in_force":"gtc",
    "created_at":"2026-01-06T16:00:00.000Z",
    "updated_at":"2026-01-08T16:00:00.000Z",
    "tag":"",
    "reject_reason":"",
    "filled_value":1183455.0,
    "duration":"P2DT0H0M0S"
  },
  {
    "id":"4d17f8c8-263b-4c94-a3c8-4865b7ee272d",
    "symbol":"BENCHMARK",
    "side":"sell",
    "order_type":"market",
    "quantity":33928.0,
    "filled_quantity":33928.0,
    "limit_price":null,
    "stop_price":null,
    "avg_price":31.33,
    "commission":159.444636,
    "status":"filled",
    "time_in_force":"gtc",
    "created_at":"2026-01-27T16:00:00.000Z",
    "updated_at":"2026-01-29T16:00:00.000Z",
    "tag":"",
    "reject_reason":"",
    "filled_value":1062964.24,
    "duration":"P2DT0H0M0S"
  },
  {
    "id":"25e0481c-4252-4d97-9815-e3bb6edc8898",
    "symbol":"BENCHMARK",
    "side":"buy",
    "order_type":"market",
    "quantity":33000.0,
    "filled_quantity":33000.0,
    "limit_price":null,
    "stop_price":null,
    "avg_price":31.91,
    "commission":157.9545,
    "status":"filled",
    "time_in_force":"gtc",
    "created_at":"2026-02-05T16:00:00.000Z",
    "updated_at":"2026-02-09T16:00:00.000Z",
    "tag":"",
    "reject_reason":"",
    "filled_value":1053030.0,
    "duration":"P4DT0H0M0S"
  },
  {
    "id":"338400e5-6c1f-40f4-8a36-e391ed69940a",
    "symbol":"BENCHMARK",
    "side":"sell",
    "order_type":"market",
    "quantity":33000.0,
    "filled_quantity":33000.0,
    "limit_price":null,
    "stop_price":null,
    "avg_price":31.05,
    "commission":153.6975,
    "status":"filled",
    "time_in_force":"gtc",
    "created_at":"2026-02-12T16:00:00.000Z",
    "updated_at":"2026-02-24T16:00:00.000Z",
    "tag":"",
    "reject_reason":"",
    "filled_value":1024650.0,
    "duration":"P12DT0H0M0S"
  }
]