[
  {
    "symbol":"BENCHMARK",
    "entry_time":"2024-06-06T16:00:00.000Z",
    "exit_time":"2024-06-25T16:00:00.000Z",
    "entry_price":0.994,
    "exit_price":0.997,
    "quantity":1000900.0,
    "side":"Long",
    "pnl":3002.7,
    "net_pnl":2703.781215,
    "return_pct":0.3018108652,
    "commission":298.918785,
    "duration_bars":12,
    "duration":"P19DT0H0M0S",
    "mae":-0.5030181087,
    "mfe":9.1549295775,
    "entry_tag":"",
    "exit_tag":"",
    "entry_portfolio_value":1004855.26581,
    "max_drawdown_pct":8.66359447
  },
  {
    "symbol":"BENCHMARK",
    "entry_time":"2024-07-09T16:00:00.000Z",
    "exit_time":"2024-07-24T16:00:00.000Z",
    "entry_price":1.02,
    "exit_price":1.034,
    "quantity":977196.0,
    "side":"Long",
    "pnl":13680.744,
    "net_pnl":13379.6699124,
    "return_pct":1.3725490196,
    "commission":301.0740876,
    "duration_bars":11,
    "duration":"P15DT0H0M0S",
    "mae":-0.4901960784,
    "mfe":8.8235294118,
    "entry_tag":"",
    "exit_tag":"",
    "entry_portfolio_value":1008417.446227,
    "max_drawdown_pct":8.5585585586
  },
  {
    "symbol":"BENCHMARK",
    "entry_time":"2024-07-31T16:00:00.000Z",
    "exit_time":"2024-08-04T16:00:00.000Z",
    "entry_price":1.065,
    "exit_price":1.04,
    "quantity":953972.0,
    "side":"Long",
    "pnl":-23849.3,
    "net_pnl":-24150.516659,
    "return_pct":-2.3474178404,
    "commission":301.216659,
    "duration_bars":2,
    "duration":"P4DT0H0M0S",
    "mae":-6.7605633803,
    "mfe":1.7840375587,
    "entry_tag":"",
    "exit_tag":"",
    "entry_portfolio_value":1015931.0541004,
    "max_drawdown_pct":8.3948339483
  },
  {
    "symbol":"BENCHMARK",
    "entry_time":"2024-09-26T16:00:00.000Z",
    "exit_time":"2024-10-16T16:00:00.000Z",
    "entry_price":0.989,
    "exit_price":1.245,
    "quantity":1002864.0,
    "side":"Long",
    "pnl":256733.184,
    "net_pnl":256397.1242736,
    "return_pct":25.8847320526,
    "commission":336.0597264,
    "duration_bars":9,
    "duration":"P20DT0H0M0S",
    "mae":-2.1233569262,
    "mfe":56.0161779575,
    "entry_tag":"",
    "exit_tag":"",
    "entry_portfolio_value":960695.375594,
    "max_drawdown_pct":21.8405703176
  },
  {
    "symbol":"BENCHMARK",
    "entry_time":"2024-10-17T16:00:00.000Z",
    "exit_time":"2024-11-03T16:00:00.000Z",
    "entry_price":1.239,
    "exit_price":1.336,
    "quantity":1007428.0,
    "side":"Long",
    "pnl":97720.516,
    "net_pnl":97331.396935,
    "return_pct":7.8288942696,
    "commission":389.119065,
    "duration_bars":11,
    "duration":"P17DT0H0M0S",
    "mae":-0.7263922518,
    "mfe":20.9846650525,
    "entry_tag":"",
    "exit_tag":"",
    "entry_portfolio_value":1248142.8282482,
    "max_drawdown_pct":11.140760507
  },
  {
    "symbol":"BENCHMARK",
    "entry_time":"2024-11-04T16:00:00.000Z",
    "exit_time":"2024-11-17T16:00:00.000Z",
    "entry_price":1.363,
    "exit_price":1.426,
    "quantity":987179.0,
    "side":"Long",
    "pnl":62192.277,
    "net_pnl":61779.29066535,
    "return_pct":4.6221570066,
    "commission":412.98633465,
    "duration_bars":9,
    "duration":"P13DT0H0M0S",
    "mae":-0.5135730007,
    "mfe":17.3881144534,
    "entry_tag":"",
    "exit_tag":"",
    "entry_portfolio_value":1344472.4479304501,
    "max_drawdown_pct":13.25
  },
  {
    "symbol":"BENCHMARK",
    "entry_time":"2024-11-19T16:00:00.000Z",
    "exit_time":"2024-11-20T16:00:00.000Z",
    "entry_price":1.452,
    "exit_price":1.441,
    "quantity":969213.0,
    "side":"Long",
    "pnl":-10661.343,
    "net_pnl":-11081.93298135,
    "return_pct":-0.7575757576,
    "commission":420.58998135,
    "duration_bars":1,
    "duration":"P1DT0H0M0S",
    "mae":-1.9972451791,
    "mfe":1.1019283747,
    "entry_tag":"",
    "exit_tag":"",
    "entry_portfolio_value":1403352.79975095,
    "max_drawdown_pct":2.4523160763
  },
  {
    "symbol":"BENCHMARK",
    "entry_time":"2024-11-21T16:00:00.000Z",
    "exit_time":"2024-11-24T16:00:00.000Z",
    "entry_price":1.446,
    "exit_price":1.388,
    "quantity":964239.0,
    "side":"Long",
    "pnl":-55925.862,
    "net_pnl":-56335.7599989,
    "return_pct":-4.0110650069,
    "commission":409.8979989,
    "duration_bars":1,
    "duration":"P3DT0H0M0S",
    "mae":-7.468879668,
    "mfe":1.1756569848,
    "entry_tag":"",
    "exit_tag":"",
    "entry_portfolio_value":1398078.1479219,
    "max_drawdown_pct":8.5440874915
  },
  {
    "symbol":"BENCHMARK",
    "entry_time":"2024-12-12T16:00:00.000Z",
    "exit_time":"2024-12-15T16:00:00.000Z",
    "entry_price":1.417,
    "exit_price":1.394,
    "quantity":945580.0,
    "side":"Long",
    "pnl":-21748.34,
    "net_pnl":-22147.043807,
    "return_pct":-1.6231474947,
    "commission":398.703807,
    "duration_bars":1,
    "duration":"P3DT0H0M0S",
    "mae":-3.3874382498,
    "mfe":0.0705716302,
    "entry_tag":"",
    "exit_tag":"",
    "entry_portfolio_value":1338876.4903331001,
    "max_drawdown_pct":3.4555712271
  },
  {
    "symbol":"BENCHMARK",
    "entry_time":"2024-12-19T16:00:00.000Z",
    "exit_time":"2025-01-01T16:00:00.000Z",
    "entry_price":1.426,
    "exit_price":1.433,
    "quantity":920212.0,
    "side":"Long",
    "pnl":6441.484,
    "net_pnl":6046.8510838,
    "return_pct":0.4908835905,
    "commission":394.6329162,
    "duration_bars":8,
    "duration":"P13DT0H0M0S",
    "mae":-5.1192145863,
    "mfe":7.4333800842,
    "entry_tag":"",
    "exit_tag":"",
    "entry_portfolio_value":1323200.4482082999,
    "max_drawdown_pct":11.684073107
  },
  {
    "symbol":"BENCHMARK",
    "entry_time":"2025-01-14T16:00:00.000Z",
    "exit_time":"2025-01-15T16:00:00.000Z",
    "entry_price":1.429,
    "exit_price":1.446,
    "quantity":922500.0,
    "side":"Long",
    "pnl":15682.5,
    "net_pnl":15284.671875,
    "return_pct":1.1896431071,
    "commission":397.828125,
    "duration_bars":1,
    "duration":"P1DT0H0M0S",
    "mae":-2.5192442267,
    "mfe":1.9594121763,
    "entry_tag":"",
    "exit_tag":"",
    "entry_portfolio_value":1329260.1227639001,
    "max_drawdown_pct":4.3925875086
  },
  {
    "symbol":"BENCHMARK",
    "entry_time":"2025-01-20T16:00:00.000Z",
    "exit_time":"2025-02-04T16:00:00.000Z",
    "entry_price":1.431,
    "exit_price":1.434,
    "quantity":935759.0,
    "side":"Long",
    "pnl":2807.277,
    "net_pnl":2405.13456975,
    "return_pct":0.2096436059,
    "commission":402.14243025,
    "duration_bars":5,
    "duration":"P15DT0H0M0S",
    "mae":-2.3060796646,
    "mfe":3.284416492,
    "entry_tag":"",
    "exit_tag":"",
    "entry_portfolio_value":1338070.9128445501,
    "max_drawdown_pct":5.4127198917
  },
  {
    "symbol":"BENCHMARK",
    "entry_time":"2025-02-05T16:00:00.000Z",
    "exit_time":"2025-03-03T16:00:00.000Z",
    "entry_price":1.433,
    "exit_price":1.546,
    "quantity":930935.0,
    "side":"Long",
    "pnl":105195.655,
    "net_pnl":104779.66669525,
    "return_pct":7.8855547802,
    "commission":415.98830475,
    "duration_bars":18,
    "duration":"P26DT0H0M0S",
    "mae":-0.1395673412,
    "mfe":16.8876482903,
    "entry_tag":"",
    "exit_tag":"",
    "entry_portfolio_value":1348860.0426054001,
    "max_drawdown_pct":9.2537313433
  },
  {
    "symbol":"BENCHMARK",
    "entry_time":"2025-03-04T16:00:00.000Z",
    "exit_time":"2025-03-13T16:00:00.000Z",
    "entry_price":1.595,
    "exit_price":1.553,
    "quantity":906737.0,
    "side":"Long",
    "pnl":-38082.954,
    "net_pnl":-38511.1152114,
    "return_pct":-2.6332288401,
    "commission":428.1612114,
    "duration_bars":7,
    "duration":"P9DT0H0M0S",
    "mae":-3.3855799373,
    "mfe":3.6990595611,
    "entry_tag":"",
    "exit_tag":"",
    "entry_portfolio_value":1443455.1859516499,
    "max_drawdown_pct":6.8319226119
  },
  {
    "symbol":"BENCHMARK",
    "entry_time":"2025-04-13T16:00:00.000Z",
    "exit_time":"2025-05-13T16:00:00.000Z",
    "entry_price":1.509,
    "exit_price":1.481,
    "quantity":932895.0,
    "side":"Long",
    "pnl":-26121.06,
    "net_pnl":-26539.4634075,
    "return_pct":-1.8555334659,
    "commission":418.4034075,
    "duration_bars":19,
    "duration":"P30DT0H0M0S",
    "mae":-3.37972167,
    "mfe":2.451954937,
    "entry_tag":"",
    "exit_tag":"",
    "entry_portfolio_value":1387146.3677842501,
    "max_drawdown_pct":4.786545925
  },
  {
    "symbol":"BENCHMARK",
    "entry_time":"2025-06-24T16:00:00.000Z",
    "exit_time":"2025-09-04T16:00:00.000Z",
    "entry_price":1.435,
    "exit_price":1.737,
    "quantity":962510.0,
    "side":"Long",
    "pnl":290678.02,
    "net_pnl":290220.057742,
    "return_pct":21.0452961672,
    "commission":457.962258,
    "duration_bars":52,
    "duration":"P72DT0H0M0S",
    "mae":0.0,
    "mfe":39.3728222997,
    "entry_tag":"",
    "exit_tag":"",
    "entry_portfolio_value":1381134.5748825001,
    "max_drawdown_pct":13.4
  },
  {
    "symbol":"BENCHMARK",
    "entry_time":"2025-09-07T16:00:00.000Z",
    "exit_time":"2025-09-08T16:00:00.000Z",
    "entry_price":1.816,
    "exit_price":1.786,
    "quantity":920370.0,
    "side":"Long",
    "pnl":-27611.1,
    "net_pnl":-28108.375911,
    "return_pct":-1.6519823789,
    "commission":497.275911,
    "duration_bars":1,
    "duration":"P1DT0H0M0S",
    "mae":-2.8083700441,
    "mfe":1.7070484581,
    "entry_tag":"",
    "exit_tag":"",
    "entry_portfolio_value":1671311.104114,
    "max_drawdown_pct":4.4396318354
  },
  {
    "symbol":"BENCHMARK",
    "entry_time":"2025-09-11T16:00:00.000Z",
    "exit_time":"2025-10-14T16:00:00.000Z",
    "entry_price":1.879,
    "exit_price":2.081,
    "quantity":864434.0,
    "side":"Long",
    "pnl":174615.668,
    "net_pnl":174102.194204,
    "return_pct":10.7503991485,
    "commission":513.473796,
    "duration_bars":17,
    "duration":"P33DT0H0M0S",
    "mae":-0.0532197978,
    "mfe":26.5566790846,
    "entry_tag":"",
    "exit_tag":"",
    "entry_portfolio_value":1662227.3442681001,
    "max_drawdown_pct":14.4659377628
  },
  {
    "symbol":"BENCHMARK",
    "entry_time":"2025-10-15T16:00:00.000Z",
    "exit_time":"2025-10-16T16:00:00.000Z",
    "entry_price":2.092,
    "exit_price":2.09,
    "quantity":866241.0,
    "side":"Long",
    "pnl":-1732.482,
    "net_pnl":-2275.8749793,
    "return_pct":-0.0956022945,
    "commission":543.3929793,
    "duration_bars":1,
    "duration":"P1DT0H0M0S",
    "mae":-3.9196940727,
    "mfe":2.0554493308,
    "entry_tag":"",
    "exit_tag":"",
    "entry_portfolio_value":1822481.2507692,
    "max_drawdown_pct":5.8548009368
  },
  {
    "symbol":"BENCHMARK",
    "entry_time":"2025-10-26T16:00:00.000Z",
    "exit_time":"2025-11-02T16:00:00.000Z",
    "entry_price":2.211,
    "exit_price":2.088,
    "quantity":820938.0,
    "side":"Long",
    "pnl":-100975.374,
    "net_pnl":-101504.7558693,
    "return_pct":-5.5630936228,
    "commission":529.3818693,
    "duration_bars":5,
    "duration":"P7DT0H0M0S",
    "mae":-8.8195386703,
    "mfe":1.7639077341,
    "entry_tag":"",
    "exit_tag":"",
    "entry_portfolio_value":1782990.910128,
    "max_drawdown_pct":10.4
  },
  {
    "symbol":"BENCHMARK",
    "entry_time":"2025-12-01T16:00:00.000Z",
    "exit_time":"2025-12-02T16:00:00.000Z",
    "entry_price":2.004,
    "exit_price":1.975,
    "quantity":854239.0,
    "side":"Long",
    "pnl":-24772.931,
    "net_pnl":-25282.78354715,
    "return_pct":-1.4471057884,
    "commission":509.85254715,
    "duration_bars":1,
    "duration":"P1DT0H0M0S",
    "mae":-2.49500998,
    "mfe":0.0499001996,
    "entry_tag":"",
    "exit_tag":"",
    "entry_portfolio_value":1715226.694103,
    "max_drawdown_pct":2.5436408978
  },
  {
    "symbol":"BENCHMARK",
    "entry_time":"2025-12-04T16:00:00.000Z",
    "exit_time":"2025-12-16T16:00:00.000Z",
    "entry_price":1.999,
    "exit_price":1.957,
    "quantity":844582.0,
    "side":"Long",
    "pnl":-35472.444,
    "net_pnl":-35973.6189588,
    "return_pct":-2.1010505253,
    "commission":501.1749588,
    "duration_bars":8,
    "duration":"P12DT0H0M0S",
    "mae":-3.0015007504,
    "mfe":2.8514257129,
    "entry_tag":"",
    "exit_tag":"",
    "entry_portfolio_value":1686549.8048865499,
    "max_drawdown_pct":5.6906614786
  },
  {
    "symbol":"BENCHMARK",
    "entry_time":"2025-12-17T16:00:00.000Z",
    "exit_time":"2026-02-02T16:00:00.000Z",
    "entry_price":1.993,
    "exit_price":2.289,
    "quantity":827000.0,
    "side":"Long",
    "pnl":244792.0,
    "net_pnl":244260.8179,
    "return_pct":14.8519819368,
    "commission":531.1821,
    "duration_bars":31,
    "duration":"P47DT0H0M0S",
    "mae":0.0,
    "mfe":27.1450075263,
    "entry_tag":"",
    "exit_tag":"",
    "entry_portfolio_value":1656406.36619045,
    "max_drawdown_pct":11.36543015
  },
  {
    "symbol":"BENCHMARK",
    "entry_time":"2026-02-26T16:00:00.000Z",
    "exit_time":"2026-03-02T16:00:00.000Z",
    "entry_price":2.348,
    "exit_price":2.31,
    "quantity":801600.0,
    "side":"Long",
    "pnl":-30460.8,
    "net_pnl":-31020.87792,
    "return_pct":-1.6183986371,
    "commission":560.07792,
    "duration_bars":2,
    "duration":"P4DT0H0M0S",
    "mae":-7.3253833049,
    "mfe":0.468483816,
    "entry_tag":"",
    "exit_tag":"",
    "entry_portfolio_value":1910925.8922204501,
    "max_drawdown_pct":7.7575243747
  }
]